pyqlops/__init__.py
pyqlops/db.py
pyqlops/db_test.py
pyqlops/example.py
pyqlops/main.py
pyqlops/utils/__init__.py
pyqlops/utils/file_name_test.py
pyqlops/utils/helpers.py
pyqlops/utils/paths.py
pyqlops-0.0.5.dist-info/licenses/LICENSE
pyqlops-0.0.5.dist-info/METADATA
pyqlops-0.0.5.dist-info/WHEEL
pyqlops-0.0.5.dist-info/top_level.txt
pyqlops-0.0.5.dist-info/RECORD
